.gitignore
LICENSE
MANIFEST.in
README.rst
requirements.txt
setup.cfg
setup.py
tadpole/__init__.py
tadpole/config.py
tadpole/init_handler.py
tadpole/logger.py
tadpole/run.py
tadpole.egg-info/PKG-INFO
tadpole.egg-info/SOURCES.txt
tadpole.egg-info/dependency_links.txt
tadpole.egg-info/entry_points.txt
tadpole.egg-info/requires.txt
tadpole.egg-info/top_level.txt
tadpole/../tadpole/template/.gitignore
tadpole/../tadpole/template/app.db
tadpole/../tadpole/template/dev.py
tadpole/../tadpole/template/main.py
tadpole/../tadpole/template/requirements.txt
tadpole/../tadpole/template/template.py
tadpole/../tadpole/template/app/__init__.py
tadpole/../tadpole/template/app/extensions/__init__.py
tadpole/../tadpole/template/app/extensions/redis_manager.py
tadpole/../tadpole/template/app/extensions/sqlalchemy.py
tadpole/../tadpole/template/app/lib/__init__.py
tadpole/../tadpole/template/app/lib/auth.py
tadpole/../tadpole/template/app/lib/constant.py
tadpole/../tadpole/template/app/lib/exceptions.py
tadpole/../tadpole/template/app/lib/pine_wrapper.py
tadpole/../tadpole/template/app/lib/rest_model.py
tadpole/../tadpole/template/app/lib/rest_route.py
tadpole/../tadpole/template/app/lib/utils.py
tadpole/../tadpole/template/app/lib/validator.py
tadpole/../tadpole/template/app/lib/database/__init__.py
tadpole/../tadpole/template/app/lib/database/utils.py
tadpole/../tadpole/template/app/lib/database/custom_types/__init__.py
tadpole/../tadpole/template/app/lib/database/custom_types/email.py
tadpole/../tadpole/template/app/lib/database/custom_types/ip_address.py
tadpole/../tadpole/template/app/lib/database/custom_types/password.py
tadpole/../tadpole/template/app/lib/logger/__init__.py
tadpole/../tadpole/template/app/lib/logger/handlers/__init__.py
tadpole/../tadpole/template/app/lib/logger/handlers/redis_handler.py
tadpole/../tadpole/template/app/models/__init__.py
tadpole/../tadpole/template/app/models/auth/__init__.py
tadpole/../tadpole/template/app/models/auth/relation.py
tadpole/../tadpole/template/app/models/auth/resource.py
tadpole/../tadpole/template/app/models/auth/role.py
tadpole/../tadpole/template/app/models/auth/user.py
