Metadata-Version: 1.1
Name: tadpole
Version: 1.0.6
Summary: flask starter
Home-page: https://github.com/echoyuanliang/tadpole
Author: allen
Author-email: echoyuanliang@gmail.com
License: MIT
Download-URL: https://github.com/echoyuanliang/tadpole.git
Keywords: flask,restful,orm,sqlalchemy,auth,permission
Platform: any
Classifier: Operating System :: POSIX
Classifier: Development Status :: 5 - Production/Stable
Classifier: Environment :: Web Environment
Classifier: Intended Audience :: Developers
Classifier: License :: OSI Approved :: MIT License
Classifier: Programming Language :: Python :: 2
Classifier: Programming Language :: Python :: 2.7
Classifier: Programming Language :: Python :: Implementation :: PyPy
